<?xml version="1.0" encoding="UTF-8" standalone="yes"?>
<ns2:GetCalendarAndFlightAvailabilityRequest xmlns:ns2="http://www.ba.com/schema/availabilitycontroller/tGetCalendarAndFlightAvailabilityV1">
    <MessageHeader/>
    <CAPHeader>
        <UserSellingProfile>
            <Audience>Agent_External</Audience>
            <SellingRevenueType>
                <CommercialRevenueType/>
            </SellingRevenueType>
        </UserSellingProfile>
    </CAPHeader>
    <CommonParameters>
        <OriginDestinationOption>
            <OriginLocationCode>LHR</OriginLocationCode>
            <OriginDateTime>2013-11-30T00:00:00Z</OriginDateTime>
            <DestinationLocationCode>AMS</DestinationLocationCode>
        </OriginDestinationOption>
        <OriginDestinationOption>
            <OriginLocationCode>AMS</OriginLocationCode>
            <OriginDateTime>2013-12-07T00:00:00Z</OriginDateTime>
            <DestinationLocationCode>LHR</DestinationLocationCode>
        </OriginDestinationOption>
        <PassengerCount>
            <NumberOfAdults>2</NumberOfAdults>
            <NumberOfChildren>2</NumberOfChildren>
            <NumberOfInfants>2</NumberOfInfants>
        </PassengerCount>
        <CabinRestriction>
            <CabinCode>M</CabinCode>
            <RestrictionType>Restricted</RestrictionType>
        </CabinRestriction>
        <OutboundDateRange>3</OutboundDateRange>
        <InboundDateRange>3</InboundDateRange>
    </CommonParameters>
    <PointOfSale>LHR</PointOfSale>
    <AvailabilityEngineSelectionCriteria>AnyFares</AvailabilityEngineSelectionCriteria>
    <TypeOfAvailabilitySearch>CombinedCalendarAndFlightAvailability</TypeOfAvailabilitySearch>
    <InitialRequest>true</InitialRequest>
    <DeadEndSchedulingRequired>true</DeadEndSchedulingRequired>
    <PointsEarningFaresFilterRequired>false</PointsEarningFaresFilterRequired>
    <InvoluntaryUpsellingRequired>true</InvoluntaryUpsellingRequired>
    <PageFlowPath>FROM_PLAN_FRAGMENT</PageFlowPath>
</ns2:GetCalendarAndFlightAvailabilityRequest>